Workbook

Sheet Inputs
A1: Item | B1: Unit Cost | C1: Qty
A2: Copy Paper A4 Rim | B2: 4.8 | C2: 12
A3: Ballpoint Pen Box | B3: 6.4 | C3: 8
A4: Stapler Pro | B4: 14.95 | C4: 3
A5: Sticky Notes Pack | B5: 3.25 | C5: 20
A6: Binder Clips Box | B6: 2.1 | C6: 15
A7: Highlighters Set | B7: 5.6 | C7: 9
A8: Desk Organizer | B8: 18.75 | C8: 2
A9: USB-C Cable 2m | B9: 9.9 | C9: 11
A10: Wireless Mouse | B10: 24.5 | C10: 4
A11: Keyboard Wired | B11: 32 | C11: 4
A12: Monitor Stand | B12: 45.95 | C12: 2
A13: Notebook A5 | B13: 3.9 | C13: 25
... A21: Trash Bin 12L | B21: 16.5 | C21: 4

Sheet Settings
A1: Markup | B1: 0.25
A2: Tax rate | B2: 0.08
A3: Unused discount | B3: 0.1
A4: Surcharge | B4: 0.15

Sheet Pricing
A1: Item | B1: Cost Total | C1: Price | D1: With Tax
A2: =Inputs!A2 | B2: =Inputs!B2*Inputs!C2 | C2: =B2*(1+Settings!$B$1) | D2: =C2+C2*Settings!$B$2
A3: =Inputs!A3 | B3: =Inputs!B3*Inputs!C3 | C3: =B3*(1+Settings!$B$1) | D3: =C3+C3*Settings!$B$2
A4: =Inputs!A4 | B4: =Inputs!B4*Inputs!C4 | C4: =B4*(1+Settings!$B$1) | D4: =C4+C4*Settings!$B$2
A5: =Inputs!A5 | B5: =Inputs!B5*Inputs!C5 | C5: =B5*(1+Settings!$B$1) | D5: =C5+C5*Settings!$B$2
A6: =Inputs!A6 | B6: =Inputs!B6*Inputs!C6 | C6: =B6*(1+Settings!$B$1) | D6: =C6+C6*Settings!$B$2
A7: =Inputs!A7 | B7: =Inputs!B7*Inputs!C7 | C7: =B7*(1+Settings!$B$1) | D7: =C7+C7*Settings!$B$2
A8: =Inputs!A8 | B8: =Inputs!B8*Inputs!C8 | C8: =B8*(1+Settings!$B$1) | D8: =C8+C8*Settings!$B$2
A9: =Inputs!A9 | B9: =Inputs!B9*Inputs!C9 | C9: =B9*(1+Settings!$B$1) | D9: =C9+C9*Settings!$B$2
A10: =Inputs!A10 | B10: =Inputs!B10*Inputs!C10 | C10: =B10*(1+Settings!$B$1) | D10: =C10+C10*Settings!$B$2
A11: =Inputs!A11 | B11: =Inputs!B11*Inputs!C11 | C11: =B11*(1+Settings!$B$1) | D11: =C11+C11*Settings!$B$2
A12: =Inputs!A12 | B12: =Inputs!B12*Inputs!C12 | C12: =B12*(1+Settings!$B$1) | D12: =C12+C12*Settings!$B$2
A13: =Inputs!A13 | B13: =Inputs!B13*Inputs!C13 | C13: 99.5 | D13: =C13+C13*Settings!$B$2
A14: =Inputs!A14 | B14: =Inputs!B14*Inputs!C14 | C14: =B14*(1+Settings!$B$1) | D14: =C14+C14*Settings!$B$2
A15: =Inputs!A15 | B15: =Inputs!B15*Inputs!C15 | C15: =B15*(1+Settings!$B$1) | D15: =C15+C15*Settings!$B$2
A16: =Inputs!A16 | B16: =Inputs!B16*Inputs!C16 | C16: =B16*(1+Settings!$B$1) | D16: =C16+C16*Settings!$B$2
A17: =Inputs!A17 | B17: =Inputs!B17*Inputs!C17 | C17: =B17*(1+Settings!$B$1) | D17: =C17+C17*Settings!$B$2
A18: =Inputs!A18 | B18: =Inputs!B18*Inputs!C18 | C18: =B18*(1+Settings!$B$1) | D18: =C18+C18*Settings!$B$2
A19: =Inputs!A19 | B19: =Inputs!B19*Inputs!C19 | C19: =B19*(1+Settings!$B$1) | D19: =C19+C19*Settings!$B$2
A20: =Inputs!A20 | B20: =Inputs!B20*Inputs!C20 | C20: =B20*(1+Settings!$B$1) | D20: =C20+C20*Settings!$B$2
A21: =Inputs!A21 | B21: =Inputs!B21*Inputs!C21 | C21: =B21*(1+Settings!$B$1) | D21: =C21+C21*Settings!$B$2

Sheet Summary
A2: Total cost | B2: =SUM(Pricing!B2:B21)
A3: Total price | B3: =SUM(Pricing!C2:C20)
A4: Total with tax | B4: =SUM(Pricing!D2:D21)
A5: Total with surcharge | B5: =B4*1.15
A7: Loop A | B7: =B8+1
A8: Loop B | B8: =B7*2
